libhermes/__init__.py
libhermes/configManager.py
libhermes/dbOperations.py
libhermes/mqttPublisher.py
libhermes-1.1.0.dist-info/LICENCE
libhermes-1.1.0.dist-info/METADATA
libhermes-1.1.0.dist-info/WHEEL
libhermes-1.1.0.dist-info/top_level.txt
libhermes-1.1.0.dist-info/RECORD
